Workbook

Sheet data
A1: typeCode | B1: freqCode | C1: refPeriodId | D1: refYear | E1: refMonth | F1: period | G1: reporterCode | H1: reporterISO | I1: reporterDesc | J1: flowCode | K1: flowDesc | L1: partnerCode | M1: partnerISO | N1: partnerDesc | O1: partner2Code | P1: partner2ISO | Q1: partner2Desc | R1: classificationCode | S1: classificationSearchCode | T1: isOriginalClassification | U1: cmdCode | V1: cmdDesc | W1: aggrLevel | X1: cifvalue | Y1: NAICS code
A2: C | B2: A | C2: 20120101 | D2: 2012 | E2: 52 | F2: 2012 | G2: 842 | H2: USA | I2: USA | J2: M | K2: Import | L2: 156 | M2: CHN | N2: China | O2: 0 | P2: W00 | Q2: World | R2: H4 | S2: HS | T2: TRUE | U2: 010611 | V2: Mammals; live, primates | W2: 6 | X2: 23228522 | Y2: =VLOOKUP(U2,concordance!B:C,2,0) -> #N/A
A3: C | B3: A | C3: 20120101 | D3: 2012 | E3: 52 | F3: 2012 | G3: 842 | H3: USA | I3: USA | J3: M | K3: Import | L3: 156 | M3: CHN | N3: China | O3: 0 | P3: W00 | Q3: World | R3: H4 | S3: HS | T3: TRUE | U3: 010619 | V3: Mammals; live, other than primates, whales, dolphins, porpoises (mammals of the order Cetacea); manatees, dugongs (mammals of the order Sirenia); seals, sea lions, walruses (mammals of the suborder Pinnipedia), camels, other camelids, rabbits and hares | W3: 6 | X3: 3525 | Y3: =VLOOKUP(U3,concordance!B:C,2,0) -> #N/A
A4: C | B4: A | C4: 20120101 | D4: 2012 | E4: 52 | F4: 2012 | G4: 842 | H4: USA | I4: USA | J4: M | K4: Import | L4: 156 | M4: CHN | N4: China | O4: 0 | P4: W00 | Q4: World | R4: H4 | S4: HS | T4: TRUE | U4: 010620 | V4: Reptiles; live (including snakes and turtles) | W4: 6 | X4: 6368 | Y4: =VLOOKUP(U4,concordance!B:C,2,0) -> #N/A
A5: C | B5: A | C5: 20120101 | D5: 2012 | E5: 52 | F5: 2012 | G5: 842 | H5: USA | I5: USA | J5: M | K5: Import | L5: 156 | M5: CHN | N5: China | O5: 0 | P5: W00 | Q5: World | R5: H4 | S5: HS | T5: TRUE | U5: 010690 | V5: Animals; live, n.e.c. in chapter 01, other than mammals, reptiles, birds and insects | W5: 6 | X5: 162720 | Y5: =VLOOKUP(U5,concordance!B:C,2,0) -> #N/A
A6: C | B6: A | C6: 20120101 | D6: 2012 | E6: 52 | F6: 2012 | G6: 842 | H6: USA | I6: USA | J6: M | K6: Import | L6: 156 | M6: CHN | N6: China | O6: 0 | P6: W00 | Q6: World | R6: H4 | S6: HS | T6: TRUE | U6: 020810 | V6: Meat and edible meat offal; of rabbits or hares, fresh, chilled or frozen | W6: 6 | X6: 2954972 | Y6: =VLOOKUP(U6,concordance!B:C,2,0) -> #N/A
A7: C | B7: A | C7: 20120101 | D7: 2012 | E7: 52 | F7: 2012 | G7: 842 | H7: USA | I7: USA | J7: M | K7: Import | L7: 156 | M7: CHN | N7: China | O7: 0 | P7: W00 | Q7: World | R7: H4 | S7: HS | T7: TRUE | U7: 020890 | V7: Meat and edible meat offal; n.e.c. in chapter 2, fresh, chilled or frozen | W7: 6 | X7: 10607548 | Y7: =VLOOKUP(U7,concordance!B:C,2,0) -> #N/A
A8: C | B8: A | C8: 20120101 | D8: 2012 | E8: 52 | F8: 2012 | G8: 842 | H8: USA | I8: USA | J8: M | K8: Import | L8: 156 | M8: CHN | N8: China | O8: 0 | P8: W00 | Q8: World | R8: H4 | S8: HS | T8: TRUE | U8: 030111 | V8: Fish; live, ornamental, freshwater | W8: 6 | X8: 1313731 | Y8: =VLOOKUP(U8,concordance!B:C,2,0) -> #N/A
A9: C | B9: A | C9: 20120101 | D9: 2012 | E9: 52 | F9: 2012 | G9: 842 | H9: USA | I9: USA | J9: M | K9: Import | L9: 156 | M9: CHN | N9: China | O9: 0 | P9: W00 | Q9: World | R9: H4 | S9: HS | T9: TRUE | U9: 030119 | V9: Fish; live, ornamental, other than freshwater | W9: 6 | X9: 46026 | Y9: =VLOOKUP(U9,concordance!B:C,2,0) -> #N/A
A10: C | B10: A | C10: 20120101 | D10: 2012 | E10: 52 | F10: 2012 | G10: 842 | H10: USA | I10: USA | J10: M | K10: Import | L10: 156 | M10: CHN | N10: China | O10: 0 | P10: W00 | Q10: World | R10: H4 | S10: HS | T10: TRUE | U10: 030243 | V10: Fish; fresh or chilled, sardines (Sardina pilchardus, Sardinops spp.), sardinella (Sardinella spp.), brisling or sprats (Sprattus sprattus), excluding fillets, livers, roes, and other fish meat of heading 0304 | W10: 6 | X10: 178395 | Y10: =VLOOKUP(U10,concordance!B:C,2,0) -> #N/A
A11: C | B11: A | C11: 20120101 | D11: 2012 | E11: 52 | F11: 2012 | G11: 842 | H11: USA | I11: USA | J11: M | K11: Import | L11: 156 | M11: CHN | N11: China | O11: 0 | P11: W00 | Q11: World | R11: H4 | S11: HS | T11: TRUE | U11: 030244 | V11: Fish; fresh or chilled, mackerel (Scomber scombrus, Scomber australasicus, Scomber japonicus), excluding fillets, livers, roes, and other fish meat of heading 0304 | W11: 6 | X11: 65097 | Y11: =VLOOKUP(U11,concordance!B:C,2,0) -> #N/A
A12: C | B12: A | C12: 20120101 | D12: 2012 | E12: 52 | F12: 2012 | G12: 842 | H12: USA | I12: USA | J12: M | K12: Import | L12: 156 | M12: CHN | N12: China | O12: 0 | P12: W00 | Q12: World | R12: H4 | S12: HS | T12: TRUE | U12: 030245 | V12: Fish; fresh or chilled, jack and horse mackerel (Trachurus spp.), excluding fillets, livers, roes, and other fish meat of heading 0304 | W12: 6 | X12: 336276 | Y12: =VLOOKUP(U12,concordance!B:C,2,0) -> #N/A
A13: C | B13: A | C13: 20120101 | D13: 2012 | E13: 52 | F13: 2012 | G13: 842 | H13: USA | I13: USA | J13: M | K13: Import | L13: 156 | M13: CHN | N13: China | O13: 0 | P13: W00 | Q13: World | R13: H4 | S13: HS | T13: TRUE | U13: 030251 | V13: Fish; fresh or chilled, cod (Gadus morhua, Gadus ogac, Gadus macrocephalus), excluding fillets, livers, roes, and other fish meat of heading 0304 | W13: 6 | X13: 77692 | Y13: =VLOOKUP(U13,concordance!B:C,2,0) -> #N/A
... A4406: C | B4406: A | C4406: 20120101 | D4406: 2012 | E4406: 52 | F4406: 2012 | G4406: 842 | H4406: USA | I4406: USA | J4406: M | K4406: Import | L4406: 156 | M4406: CHN | N4406: China | O4406: 0 | P4406: W00 | Q4406: World | R4406: H4 | S4406: HS | T4406: TRUE | U4406: 999999 | V4406: Commodities not specified according to kind | W4406: 6 | X4406: 4475883674 | Y4406: =VLOOKUP(U4406,concordance!B:C,2,0) -> #N/A

Sheet NAICS import
A1: NAICS 2012
A2: 1111 | B2: =SUMIF(data!Y:Y,'NAICS import'!A2,data!X:X) -> 91986171
A3: 1112 | B3: =SUMIF(data!Y:Y,'NAICS import'!A3,data!X:X) -> 111913992
A4: 1113 | B4: =SUMIF(data!Y:Y,'NAICS import'!A4,data!X:X) -> 47771799
A5: 1114 | B5: =SUMIF(data!Y:Y,'NAICS import'!A5,data!X:X) -> 8609902
A6: 1119 | B6: =SUMIF(data!Y:Y,'NAICS import'!A6,data!X:X) -> 98697658
A7: 1121 | B7: =SUMIF(data!Y:Y,'NAICS import'!A7,data!X:X) -> 0
A8: 1122 | B8: =SUMIF(data!Y:Y,'NAICS import'!A8,data!X:X) -> 0
A9: 1123 | B9: =SUMIF(data!Y:Y,'NAICS import'!A9,data!X:X) -> 0
A10: 1124 | B10: =SUMIF(data!Y:Y,'NAICS import'!A10,data!X:X) -> 41129
A11: 1125 | B11: =SUMIF(data!Y:Y,'NAICS import'!A11,data!X:X) -> 0
A12: 1129 | B12: =SUMIF(data!Y:Y,'NAICS import'!A12,data!X:X) -> 370660
A13: 1133 | B13: =SUMIF(data!Y:Y,'NAICS import'!A13,data!X:X) -> 3237183
... A108: 9900 | B108: =SUMIF(data!Y:Y,'NAICS import'!A108,data!X:X) -> 1191380138

Sheet concordance
A1: year | B1: HS4 | C1: NAICS 2012
A2: 2012 | B2: 120190 | C2: 1111
A3: 2012 | B3: 120110 | C3: 1111
A4: 2012 | B4: 120590 | C4: 1111
A5: 2012 | B5: 120600 | C5: 1111
A6: 2012 | B6: 120400 | C6: 1111
A7: 2012 | B7: 120791 | C7: 1111
A8: 2012 | B8: 120510 | C8: 1111
A9: 2012 | B9: 120799 | C9: 1111
A10: 2012 | B10: 120750 | C10: 1111
A11: 2012 | B11: 120740 | C11: 1111
A12: 2012 | B12: 713332 | C12: 1111
A13: 2012 | B13: 713601 | C13: 1111
... A6504: 2012 | B6504: 370510 | C6504: 9900
